setup.py
ecog/__init__.py
ecog/client.py
ecog/ecogwiki.py
ecog/sample.py
ecog/version.py
ecog.egg-info/PKG-INFO
ecog.egg-info/SOURCES.txt
ecog.egg-info/dependency_links.txt
ecog.egg-info/requires.txt
ecog.egg-info/top_level.txt
scripts/ecog