Metadata-Version: 1.1
Name: ecog
Version: 0.8.1
Summary: Ecogwiki OAuth client
Home-page: https://github.com/jangxyz/ecogwiki-client
Author: Jang-hwan Kim
Author-email: janghwan@gmail.com
License: MIT License
Keywords: oauth,markdown
Platform: POSIX
Classifier: Development Status :: 3 - Alpha
Classifier: Environment :: Console
Classifier: Intended Audience :: Developers
Classifier: Intended Audience :: End Users/Desktop
Classifier: License :: OSI Approved :: MIT License
Classifier: Natural Language :: English
Classifier: Operating System :: POSIX
Classifier: Programming Language :: Python :: 2.7
Classifier: Topic :: Communications
Classifier: Topic :: Terminals
Classifier: Topic :: Text Processing
Classifier: Topic :: Utilities
